<?xml version="1.0" encoding="UTF-8"?>
<typeSystemDescription xmlns="http://uima.apache.org/resourceSpecifier">
    <name>ArticleTypeSystem</name>
    <description/>
    <version>1.0</version>
    <vendor>Webis</vendor>
  <imports>
    <import name="uima-descriptors.type-systems.CoreTypeSystem"/>
  </imports>
  <types>
    <typeDescription>
      <name>de.aitools.ie.uima.type.article.Title</name>
      <description>The title of the article.</description>
      <supertypeName>de.aitools.ie.uima.type.supertype.Unit</supertypeName>
    </typeDescription>
    <typeDescription>
      <name>de.aitools.ie.uima.type.article.MainText</name>
      <description>The main text of the article.</description>
      <supertypeName>de.aitools.ie.uima.type.supertype.Unit</supertypeName>
    </typeDescription>
    <typeDescription>
      <name>de.aitools.ie.uima.type.article.Quote</name>
      <description>This unit is a quote from someone or somewhere.</description>
      <supertypeName>de.aitools.ie.uima.type.supertype.Unit</supertypeName>
    </typeDescription>
    <typeDescription>
      <name>de.aitools.ie.uima.type.article.Link</name>
      <description>This unit is a hyperlink.</description>
      <supertypeName>de.aitools.ie.uima.type.supertype.Unit</supertypeName>
      <features>
        <featureDescription>
          <name>href</name>
          <description>The target of the link.</description>
          <rangeTypeName>uima.cas.String</rangeTypeName>
        </featureDescription>
      </features>
    </typeDescription>
    <typeDescription>
      <name>de.aitools.ie.uima.type.article.ArticleMetaData</name>
      <description>Contains meta data on the article.</description>
      <supertypeName>de.aitools.ie.uima.type.core.SourceDocumentInformation</supertypeName>
      <features>
        <featureDescription>
          <name>veracity</name>
          <description>Whether the article is "mostly false", "mix of true and false", "mostly true", or "no factual content".</description>
          <rangeTypeName>uima.cas.String</rangeTypeName>
        </featureDescription>
        <featureDescription>
          <name>portal</name>
          <description>The portal that released the article.</description>
          <rangeTypeName>uima.cas.String</rangeTypeName>
        </featureDescription>
        <featureDescription>
          <name>author</name>
          <description>The name of the author of the article.</description>
          <rangeTypeName>uima.cas.String</rangeTypeName>
        </featureDescription>
      <featureDescription>
          <name>orientation</name>
          <description>The political orientation of a portal. Can be left/right/mainstream/fake news/satire/... .</description>
          <rangeTypeName>uima.cas.String</rangeTypeName>
        </featureDescription>
      </features>
    </typeDescription>
  </types>
</typeSystemDescription>
